ndl/NNetwork.py
ndl/__init__.py
ndl/ndl.py
ndl/onmf.py
ndl/utils/__init__.py
ndl/utils/utils.py
ndlearn-0.0.2.dist-info/LICENSE
ndlearn-0.0.2.dist-info/METADATA
ndlearn-0.0.2.dist-info/WHEEL
ndlearn-0.0.2.dist-info/top_level.txt
ndlearn-0.0.2.dist-info/RECORD
