Metadata-Version: 2.1
Name: ndlearn
Version: 0.0.2
Summary: Learning from and reconstructing networks using Nonnegative Matrix Factorization
Home-page: https://github.com/jvendrow/Network-Dictionary-Learning
Author: Joshua Vendrow
Author-email: jvendrow@math.ucla.edu
License: MIT
Keywords: ndlearn
Platform: UNKNOWN
Classifier: Development Status :: 2 - Pre-Alpha
Classifier: Intended Audience :: Science/Research 
Classifier: License :: OSI Approved :: MIT License
Classifier: Natural Language :: English
Classifier: Programming Language :: Python
Classifier: Programming Language :: Python :: 3
Classifier: Programming Language :: Python :: 3 :: Only
Classifier: Programming Language :: Python :: 3.6
Classifier: Programming Language :: Python :: 3.7
Classifier: Programming Language :: Python :: 3.8
Classifier: Topic :: Scientific/Engineering
Requires-Python: >=3.6
Requires-Dist: numpy
Requires-Dist: networkx
Requires-Dist: scipy
Requires-Dist: scikit-learn
Requires-Dist: matplotlib
Requires-Dist: tqdm
Requires-Dist: psutil
Requires-Dist: tensorly
Provides-Extra: all
Requires-Dist: numpy ; extra == 'all'
Requires-Dist: networkx ; extra == 'all'
Requires-Dist: scipy ; extra == 'all'
Requires-Dist: scikit-learn ; extra == 'all'
Requires-Dist: matplotlib ; extra == 'all'
Requires-Dist: tqdm ; extra == 'all'
Requires-Dist: psutil ; extra == 'all'
Requires-Dist: tensorly ; extra == 'all'
Requires-Dist: bump2version (>=1.0.0) ; extra == 'all'
Requires-Dist: ipython (>=7.5.0) ; extra == 'all'
Requires-Dist: twine (>=1.13.0) ; extra == 'all'
Requires-Dist: wheel (>=0.33.1) ; extra == 'all'
Provides-Extra: dev
Requires-Dist: numpy ; extra == 'dev'
Requires-Dist: networkx ; extra == 'dev'
Requires-Dist: scipy ; extra == 'dev'
Requires-Dist: scikit-learn ; extra == 'dev'
Requires-Dist: matplotlib ; extra == 'dev'
Requires-Dist: tqdm ; extra == 'dev'
Requires-Dist: psutil ; extra == 'dev'
Requires-Dist: tensorly ; extra == 'dev'
Requires-Dist: bump2version (>=1.0.0) ; extra == 'dev'
Requires-Dist: ipython (>=7.5.0) ; extra == 'dev'
Requires-Dist: twine (>=1.13.0) ; extra == 'dev'
Requires-Dist: wheel (>=0.33.1) ; extra == 'dev'
Provides-Extra: docs
Provides-Extra: setup
Provides-Extra: test
Requires-Dist: numpy ; extra == 'test'
Requires-Dist: networkx ; extra == 'test'
Requires-Dist: scipy ; extra == 'test'
Requires-Dist: scikit-learn ; extra == 'test'
Requires-Dist: matplotlib ; extra == 'test'
Requires-Dist: tqdm ; extra == 'test'
Requires-Dist: psutil ; extra == 'test'
Requires-Dist: tensorly ; extra == 'test'
